nebis/__init__.py
nebis/cli.py
nebis_cli-1.1.0.dist-info/LICENSE
nebis_cli-1.1.0.dist-info/METADATA
nebis_cli-1.1.0.dist-info/WHEEL
nebis_cli-1.1.0.dist-info/entry_points.txt
nebis_cli-1.1.0.dist-info/top_level.txt
nebis_cli-1.1.0.dist-info/RECORD
