Metadata-Version: 2.1
Name: nebis-cli
Version: 1.1.0
Summary: Terminal client for Nebis Cloud, in-memory database with disk persistence.
Home-page: https://github.com/livrasand/nebis-cli
Author: NebisDB
Author-email: nebisdb@gmail.com
Classifier: Programming Language :: Python :: 3
Classifier: License :: OSI Approved :: GNU General Public License v3 (GPLv3)
Classifier: Operating System :: OS Independent
Requires-Python: >=3.6
License-File: LICENSE
Requires-Dist: requests
